breadify/__init__.py
breadify/breadify.py
breadify/cli.py
breadify-1.0.0.dist-info/METADATA
breadify-1.0.0.dist-info/WHEEL
breadify-1.0.0.dist-info/entry_points.txt
breadify-1.0.0.dist-info/top_level.txt
breadify-1.0.0.dist-info/RECORD
