Metadata-Version: 2.1
Name: breadify
Version: 1.0.0
Summary: A meme Python library that breadifies your text
Home-page: https://github.com/venkatengineer/breadify
Author: Venkat
Requires-Python: >=3.6
